ordinal_number/__init__.py
ordinal_number/ordinal_number.py
ordinal_number-0.2.dist-info/METADATA
ordinal_number-0.2.dist-info/WHEEL
ordinal_number-0.2.dist-info/top_level.txt
ordinal_number-0.2.dist-info/RECORD
