Metadata-Version: 2.1
Name: ordinal-number
Version: 0.2
Summary: A package to use OrdinnalNumber
Home-page: https://github.com/OrdinalNumber/ordinal
Author-email: alphagameplayerpro@gmail.com
License: MIT
Platform: UNKNOWN
